githubactions/__init__.py
githubactions/core/__init__.py
githubactions/core/command.py
githubactions/core/constants.py
githubactions/github/__init__.py
githubactions/github/context.py
githubactions-0.0.6.dist-info/LICENSE
githubactions-0.0.6.dist-info/METADATA
githubactions-0.0.6.dist-info/WHEEL
githubactions-0.0.6.dist-info/top_level.txt
githubactions-0.0.6.dist-info/RECORD
